Metadata-Version: 2.1
Name: deepface
Version: 0.0.98
Summary: A Lightweight Face Recognition and Facial Attribute Analysis Framework (Age, Gender, Emotion, Race) for Python
Home-page: https://github.com/serengil/deepface
Author: Sefik Ilkin Serengil
Author-email: serengil@gmail.com
License: MIT
Platform: UNKNOWN
Classifier: Programming Language :: Python :: 3
Classifier: License :: OSI Approved :: MIT License
Classifier: Operating System :: OS Independent
Requires-Python: >=3.7
License-File: LICENSE
